{
  "header-in-container": true,
  "heading": "Prénom Nom",
  "heading-subtitle": {
    "items": [
      {
        "content": "Rôle de fonction"
      }
    ]
  },
  "extras": {
    "list": [
      {
        "listItemClass": "list-item-description",
        "listItemAction": false,
        "listItemLabel": "Parti",
        "listItemContent": {
          "itemContent": "Nom du parti",
          "extraContent": false
        }
      },
      {
        "listItemClass": "list-item-description",
        "listItemAction": false,
        "listItemLabel": "Arrondissement",
        "listItemContent": {
          "itemContent": "Nom-de-l'Arrondissement",
          "extraContent": false
        }
      },
      {
        "listItemClass": "list-item-description",
        "listItemAction": false,
        "listItemLabel": "District",
        "listItemContent": {
          "itemContent": "Nom du district",
          "extraContent": false
        }
      }
    ]
  },
  "headingImg": {
    "src": "https://picsum.photos/id/1005/350/350",
    "alt": "Alt text"
  }
}
