{
  "contentHeaderClasses": "bg-gray-sky",
  "text-elements": {
    "headings":{
      "display":{
        "content": "Template événement"
      }
    }
  },
  "has-header-meta": true,
  "has-publication-date": false,
  "has-informations": true,
  "has-hub-link": {
    "url": "#",
    "link-text": "Tous les événements"
  },
  
  "informations-event": {
    "date": "Du 12 au 18 septembre 2018",
    "lieu": "Maison de la culture Ahuntsic-Cartierville"
  },
  "badges":[
    {
      "badge": "Catégorie",
      "badgeClass": "",
      "badgeUrl": "#"
    }
  ],
  "has-image": true,
  "has-documents": true,
  "has-gallery": true,
  "has-video": true,
  "social-media-icons-list": {
    "has-label": false,
    "has-facebook": true,
    "has-instagram": false,
    "has-twitter": true,
    "has-linkedin": true,
    "has-youtube": false
  },
  "mediaGallery": [
    {
      "mediaSrc": "https://picsum.photos/2000/990?image=1072",
      "mediaSize": "2000x990",
      "mediaCaption": "This is a dummy caption",
      "mediaAuthor": "Jamie Mink",
      "mediaAlt": "Media #1070",
      "thumbnail" : {
        "mediaSrc": "https://picsum.photos/600/400?image=1072",
        "height": "400",
        "width": "600"
      }
    },
    {
      "mediaSrc": "https://picsum.photos/1000/667?image=1071",
      "mediaSize": "1000x667",
      "mediaCaption": "This is a dummy caption",
      "mediaAuthor": "Tim Stief",
      "mediaAlt": "Media #1071",
      "thumbnail" : {
        "mediaSrc": "https://picsum.photos/600/400?image=1071",
        "height": "400",
        "width": "600"
      }
    },
    {
      "mediaSrc": "https://picsum.photos/1000/667?image=1070",
      "mediaSize": "1000x667",
      "mediaCaption": "This is a dummy caption",
      "mediaAuthor": "Sean Stratton",
      "mediaAlt": "Media #1070",
      "thumbnail" : {
        "mediaSrc": "https://picsum.photos/600/400?image=1070",
        "height": "400",
        "width": "600"
      }
    },
    {
      "mediaSrc": "https://picsum.photos/1000/667?image=943",
      "mediaSize": "1000x667",
      "mediaCaption": "This is a dummy caption",
      "mediaAuthor": "Paul Earle",
      "mediaAlt": "Media #943",
      "thumbnail" : {
        "mediaSrc": "https://picsum.photos/600/400?image=943",
        "height": "400",
        "width": "600"
      }
    },
    {
      "mediaSrc": "https://picsum.photos/1350/901?image=767",
      "mediaSize": "1350x901",
      "mediaCaption": "This is a dummy caption",
      "mediaAuthor": "Sébastien Marchand",
      "mediaAlt": "Media #767",
      "thumbnail" : {
        "mediaSrc": "https://picsum.photos/600/400?image=767",
        "height": "400",
        "width": "600"
      }
    },
    {
      "mediaSrc": "https://picsum.photos/1350/901?image=655",
      "mediaSize": "1350x901",
      "mediaCaption": "This is a dummy caption",
      "mediaAuthor": "Kyle Szegedi",
      "mediaAlt": "Media #655",
      "thumbnail" : {
        "mediaSrc": "https://picsum.photos/600/400?image=655",
        "height": "400",
        "width": "600"
      }
    }
  ],
  "has-tags": false,
  "tags": [
    {
      "badge": "Mot-clé #1",
      "badgeClass": "",
      "badgeUrl": "#"
    },
    {
      "badge": "Mot-clé #2",
      "badgeClass": "",
      "badgeUrl": "#"
    },
    {
      "badge": "Mot-clé #3",
      "badgeClass": "",
      "badgeUrl": "#"
    }
  ]
}
