{
  "contentHeaderContainerClasses": "container-fluid container-fluid-xl",
  "text-elements": {
    "headings": {
      "display": {
        "tag": "h1",
        "classes": "display-1",
        "content": "Display heading 1"
      }
    }
  },
  "has-lead-text" : false,
  "has-header-liner": true,
  "hasPagination": true,
  "featuredSection": {
    "cards": {
      "section-classes": "bg-gray-sky",
      "classes": false,
      "bsgrid-classes": "col-12 col-md-6 col-lg-4",
      "headings": {
        "text": "Section heading",
        "class": "section-heading"
      },
      "card-item" : [
        {
          "classes" : false,
          "url" : "#",
          "card-title" : "Acheter un permis",
          "card-text" : false,
          "card-media" : {
            "icon" : "vdm-083-permis-animal-chien"
          }
        },
        {
          "classes" : false,
          "url" : "#",
          "card-title" : "Demander un permis",
          "card-text" : false,
          "card-media" : {
            "icon" : "vdm-040-permis-generique"
          }
        },
        {
          "classes" : false,
          "url" : "#",
          "card-title" : "Collecte de résidus",
          "card-text" : false,
          "card-media" : {
            "icon" : "vdm-082-residus-verts"
          }
        },
        {
          "classes" : false,
          "url" : "#",
          "card-title" : "Réserver un livre",
          "card-text" : false,
          "card-media" : {
            "icon" : "vdm-013-livre"
          }
        },
        {
          "classes" : false,
          "url" : "#",
          "card-title" : "Transport",
          "card-text" : false,
          "card-media" : {
            "icon" : "vdm-011-bus"
          }
        },
        {
          "classes" : false,
          "url" : "#",
          "card-title" : "Payer un constat",
          "card-text" : false,
          "card-media" : {
            "icon" : "vdm-019-document"
          }
        }
      ]
    }
  },
  "inputGroupSearch": [
    {
      "formGroupLabel": false,
      "inputID": "input-group-search",
      "inputGroupIconClass": "input-group-icon-left",
      "iconAfter": false,
      "icon-label": "002-recherche",
      "formControlClass": "form-control-lg form-control-dark",
      "inputPlaceholder": "Rechercher un service"
    }
  ],
  "demandesListes": {
    "headings": {
      "text": "Section heading"
    },
    "listGroupClass": "list-group-hub",
    "listGroups": [
      {
        "listGroup": [
          {
            "url": "#",
            "title": "Consulter le rôle foncier et les ventes de propriété",
            "infos": {
              "infos-items": [
                {
                  "class": false,
                  "text": "Vous possédez un ou plusieurs immeubles à Montréal et souhaitez consulter le rôle foncier et les ventes de propriétés dans votre secteur? Voici tout ce que vous devez savoir."
                }
              ]
            }
          },
          {
            "url": "#",
            "title": "Demander l'accès aux documents des organismes publics",
            "infos": {
              "infos-items": [
                {
                  "class": false,
                  "text": "Lorem ipsum dolor sit amet, consectetur adipiscing elit. Donec non justo sit amet quam scelerisque blandit. In eu dapibus enim."
                }
              ]
            }
          },
          {
            "url": "#",
            "title": "Maecenas semper felis ut dui iaculis laoreet",
            "infos": {
              "infos-items": [
                {
                  "class": false,
                  "text": "Lorem ipsum dolor sit amet, consectetur adipiscing elit. Donec non justo sit amet quam scelerisque blandit. In eu dapibus enim."
                }
              ]
            }
          },
          {
            "url": "#",
            "title": "Integer mi mi, condimentum eu fermentum rhoncus, mollis eu sem",
            "infos": {
              "infos-items": [
                {
                  "class": false,
                  "text": "Lorem ipsum dolor sit amet, consectetur adipiscing elit. Donec non justo sit amet quam scelerisque blandit. In eu dapibus enim."
                }
              ]
            }
          },
          {
            "url": "#",
            "title": "Nulla nec purus dictum lectus molestie viverra",
            "infos": {
              "infos-items": [
                {
                  "class": false,
                  "text": "Lorem ipsum dolor sit amet, consectetur adipiscing elit. Donec non justo sit amet quam scelerisque blandit. In eu dapibus enim."
                }
              ]
            }
          },
          {
            "url": "#",
            "title": "Les parcs-nature de Montréal : planifiez votre été sans quitter l’île!",
            "infos": {
              "infos-items": [
                {
                  "class": false,
                  "text": "Lorem ipsum dolor sit amet, consectetur adipiscing elit. Donec non justo sit amet quam scelerisque blandit. In eu dapibus enim."
                }
              ]
            }
          },
          {
            "url": "#",
            "title": "Donec tempor feugiat urna",
            "infos": {
              "infos-items": [
                {
                  "class": false,
                  "text": "Lorem ipsum dolor sit amet, consectetur adipiscing elit. Donec non justo sit amet quam scelerisque blandit. In eu dapibus enim."
                }
              ]
            }
          },
          {
            "url": "#",
            "title": "Pellentesque tortor eros, tristique a aliquet at, viverra et ex",
            "infos": {
              "infos-items": [
                {
                  "class": false,
                  "text": "Lorem ipsum dolor sit amet, consectetur adipiscing elit. Donec non justo sit amet quam scelerisque blandit. In eu dapibus enim."
                }
              ]
            }
          }
        ]
      }
    ],
    "cards": {
      "section-classes": "",
      "classes": "",
      "bsgrid-classes": "col-12",
      "headings": {
        "text": "Section headings",
        "class": "section-heading"
      },
      "card-item" : [
        {
          "classes": "card-fw card-row-layout",
          "url": "#",
          "card-title": "Card with a very long title. Footer is place to the right for larger breakpoint.",
          "card-text":
            "Some quick example text to build on the card title and make up the bulk of the card's content.",
          "card-media": {
            "classes" : false,
            "icon": false
          },
          "footer" : {
            "outside-body": true
          }
        },
        {
          "classes": "card-fw card-row-layout",
          "url": "#",
          "card-title": "Card with a very long title. Footer is place to the right for larger breakpoint.",
          "card-text":
            "Some quick example text to build on the card title and make up the bulk of the card's content.",
          "card-media": {
            "classes" : false,
            "icon": false
          },
          "footer" : {
            "outside-body": true
          }
        },
        {
          "classes": "card-fw card-row-layout",
          "url": "#",
          "card-title": "Card with a very long title. Footer is place to the right for larger breakpoint.",
          "card-text":
            "Some quick example text to build on the card title and make up the bulk of the card's content.",
          "card-media": {
            "classes" : false,
            "icon": false
          },
          "footer" : {
            "outside-body": true
          }
        },
        {
          "classes": "card-fw card-row-layout",
          "url": "#",
          "card-title": "Card with a very long title. Footer is place to the right for larger breakpoint.",
          "card-text":
            "Some quick example text to build on the card title and make up the bulk of the card's content.",
          "card-media": {
            "classes" : false,
            "icon": false
          },
          "footer" : {
            "outside-body": true
          }
        },
        {
          "classes": "card-fw card-row-layout",
          "url": "#",
          "card-title": "Card with a short title.",
          "card-text":
            "Small description.",
          "card-media": {
            "classes" : false,
            "icon": false
          },
          "footer" : {
            "outside-body": true
          }
        },
        {
          "classes": "card-fw card-row-layout",
          "url": "#",
          "card-title": "Card with a very long title. Footer is place to the right for larger breakpoint.",
          "card-text":
            "Some quick example text to build on the card title and make up the bulk of the card's content.",
          "card-media": {
            "classes" : false,
            "icon": false
          },
          "footer" : {
            "outside-body": true
          }
        }
      ]
    }
  }
}
