{
  "regionMainClasses": "",
  "sidebarRight": true,
  "sidebarLeft": false,
  "navDashboard": [
    {
      "navDashboardLabel": "Tâche 1",
      "navDashboardTitle": "Titre de la tâche #1",
      "navDashboardInfo": "Information sur la tâche #1",
      "hasFeedback": false,
      "hasButton": true,
      "buttonText": "Modifier",
      "buttonClass": "btn-link",
      "hasComplete": true
    },
    {
      "navDashboardLabel": "Tâche 2",
      "navDashboardTitle": "Titre de la tâche #2",
      "navDashboardInfo": "Information sur la tâche #2",
      "hasFeedback": true,
      "removeProgressText": false,
      "progressCompleteText": "Compléter à 32%",
      "ariaNow": 32,
      "hasButton": true,
      "buttonText": "Continuer",
      "buttonClass": "btn-primary"
    },
    {
      "navDashboardLabel": "Tâche 3",
      "navDashboardTitle": "Titre de la tâche #3",
      "navDashboardInfo": "Information sur la tâche #3",
      "hasFeedback": false,
      "hasButton": false
    }
  ]
}
