{
  "navbarFixedTop": true,
  "pageClasses": false,
  "includeValidation": true,
  "breadcrumbs": [
    {
      "url": "#",
      "text": "Accueil"
    },
    {
      "url": "#",
      "text": "Élus"
    }
  ],
  "header-in-container": false,
  "heading": "Prénom-Prénom Nom-Nom",
  "module-content": [
    {
      "title": "Responsabilités",
      "list": [
        {
          "hasIcon": true,
          "icon-name": "icon-dot-bullet",
          "listItemAction": false,
          "listItemLabel": "Role de fonction",
          "listExtraContent": {
            "extraContentAction": {
              "url": "#",
              "text": "Conseil, comité ou commission"
            },
            "extraContentBold": false,
            "extraContent": "Stet diam amet duo diam dolor, nonumy dolore lorem clita voluptua, amet consetetur kasd dolore."
          }
        },
        {
          "hasIcon": true,
          "icon-name": "icon-dot-bullet",
          "listItemAction": false,
          "listItemLabel": "Role de fonction",
          "listExtraContent": {
            "extraContentAction": {
              "url": "#",
              "text": "Conseil, comité ou commission"
            },
            "extraContentBold": false,
            "extraContent": "Stet diam amet duo diam dolor, nonumy dolore lorem clita voluptua, amet consetetur kasd dolore."
          }
        },
        {
          "hasIcon": true,
          "icon-name": "icon-dot-bullet",
          "listItemAction": false,
          "listItemLabel": "Role de fonction",
          "listExtraContent": {
            "extraContentAction": {
              "url": "#",
              "text": "Conseil, comité ou commission"
            },
            "extraContentBold": false,
            "extraContent": "Stet diam amet duo diam dolor, nonumy dolore lorem clita voluptua, amet consetetur kasd dolore."
          }
        }
      ]
    },
    {
      "title": "Autres fonctions",
      "list": [
        {
          "hasIcon": true,
          "icon-name": "icon-dot-bullet",
          "listItemAction": false,
          "listItemLabel": false,
          "listExtraContent": {
            "extraContentBold": false,
            "extraContent": "Ea tempor stet vero stet diam. Et ipsum diam ipsum."
          }
        },
        {
          "hasIcon": true,
          "icon-name": "icon-dot-bullet",
          "listItemAction": false,
          "listItemLabel": false,
          "listExtraContent": {
            "extraContentBold": false,
            "extraContent": "Ea tempor stet vero stet diam. Et ipsum diam ipsum."
          }
        },
        {
          "hasIcon": true,
          "icon-name": "icon-dot-bullet",
          "listItemAction": false,
          "listItemLabel": false,
          "listExtraContent": {
            "extraContentBold": false,
            "extraContent": "Ea tempor stet vero stet diam. Et ipsum diam ipsum."
          }
        }
      ]
    }
  ],
  "sidebarRight": true,
  "sidebarClasses": false,
  "sb-classes": "",
  "sb-block-coordonnees": {
    "sb-block-contact": [
      {
        "list": [
          {
            "hasIcon": true,
            "icon-name": "icon-location",
            "listItemAction": false,
            "listItemLabel": "Nom du lieu",
            "listExtraContent": {
              "extraContentBold": "Bureau administratif (optionnel)",
              "extraContent" :"1441, rue Saint-Urbain<br>4e étage<br>Montréal (Québec) H2X 2M6"
            }
          },
          {
            "hasIcon": true,
            "icon-name": "icon-phone",
            "listItemAction": false,
            "listItemLabel": "514 555-5555"
          },
          {
            "hasIcon": true,
            "icon-name": "icon-email",
            "listItemAction": true,
            "url": "mailto:test@montreal.ca",
            "listItemLabel": "Envoyer un courriel"
          }
        ]
      },
      {
        "list": [
          {
            "hasIcon": true,
            "icon-name": "icon-location",
            "listItemAction": false,
            "listItemLabel": "Nom du lieu",
            "listExtraContent": {
              "extraContent": "1441, rue Saint-Urbain<br>4e étage<br>Montréal (Québec) H2X 2M6"
            }
          },
          {
            "hasIcon": true,
            "icon-name": "icon-phone",
            "listItemAction": false,
            "listItemLabel": "514 555-5555"
          },
          {
            "hasIcon": true,
            "icon-name": "icon-email",
            "listItemAction": true,
            "url": "mailto:test@montreal.ca",
            "listItemLabel": "Envoyer un courriel"
          }
        ]
      }
    ]
  },
  "sb-block-ms": [
    {
      "list": [
        {
          "hasIcon": true,
          "icon-name": "icon-social-facebook",
          "listItemAction": true,
          "url": "https://facebook.com",
          "listItemLabel": "Facebook"
        },
        {
          "hasIcon": true,
          "icon-name": "icon-social-linkedin",
          "listItemAction": true,
          "url": "https://linkedin.com",
          "listItemLabel": "LinkedIn"
        },
        {
          "hasIcon": true,
          "icon-name": "icon-social-twitter",
          "listItemAction": true,
          "url": "https://twitter.com",
          "listItemLabel": "Twitter"
        }
      ]
    }
  ]
}
